<?xml version="1.0" encoding="UTF-8"?>
<ReportSnapshot Major="1" Minor="0" Revision="1">
	<CoIDs>
		<CoID Type="RepNo">F2D71</CoID>
		<CoID Type="CompanyName">Momo Inc (ADR)</CoID>
		<CoID Type="CIKNo">0001610601</CoID>
	</CoIDs>
	<Issues>
		<Issue ID="1" Type="C" Desc="Common Stock" Order="1">
			<IssueID Type="Name">ADR Class A</IssueID>
			<IssueID Type="Ticker">MOMO</IssueID>
			<IssueID Type="CUSIP">60879B107</IssueID>
			<IssueID Type="ISIN">US60879B1070</IssueID>
			<IssueID Type="RIC">MOMO.O</IssueID>
			<IssueID Type="SEDOL">BSS6HX7</IssueID>
			<IssueID Type="DisplayRIC">MOMO.OQ</IssueID>
			<IssueID Type="InstrumentPI">172057266</IssueID>
			<IssueID Type="QuotePI">172066550</IssueID>
			<Exchange Code="NASD" Country="USA">NASDAQ</Exchange>
			<GlobalListingType SharesPerListing="2.0">ADR</GlobalListingType>
		</Issue>
		<Issue ID="2" Type="C" Desc="Common Stock" Order="2">
			<IssueID Type="Name">Ordinary Shares</IssueID>
			<IssueID Type="InstrumentPI">174170045</IssueID>
			<Exchange Code="NA" Country="">Not Available</Exchange>
		</Issue>
		<Issue ID="3" Type="C" Desc="Common Stock" Order="3">
			<IssueID Type="Name">Ordinary Shares</IssueID>
			<IssueID Type="InstrumentPI">192898874</IssueID>
			<Exchange Code="NA" Country="">Not Available</Exchange>
		</Issue>
	</Issues>
	<CoGeneralInfo>
		<CoStatus Code="1">Active</CoStatus>
		<CoType Code="EQU">Equity Issue</CoType>
		<LastModified>2017-06-29</LastModified>
		<LatestAvailableAnnual>2016-12-31</LatestAvailableAnnual>
		<LatestAvailableInterim>2017-03-31</LatestAvailableInterim>
		<Employees LastUpdated="2016-12-31">924</Employees>
		<SharesOut Date="2017-03-31" TotalFloat="16000000.0">394312495.0</SharesOut>
		<ReportingCurrency Code="USD">U.S. Dollars</ReportingCurrency>
		<MostRecentExchange Date="2017-08-14">1.0</MostRecentExchange>
	</CoGeneralInfo>
	<TextInfo>
		<Text Type="Business Summary" lastModified="2016-06-13T05:09:09">Momo Inc. is a holding company. The Company operates Momo, a mobile-based social networking platform. The Company's Momo platform includes its Momo mobile application and a range of related features, functionalities, tools and services that it provides to users, customers and platform partners. Momo users can maintain their relationships through its private and group communication tools, content creation and sharing functions, as well as the offline social activities promoted on its platform. It also offers live music and entertainment broadcasts on its Momo platform. The Momo mobile application, which is available on android, iPhone operating system (iOS) and Windows platforms, enables users to establish social relationships based on locations and interests. Momo offers a personal way for users to discover people nearby, and the Company facilitates the connecting, communicating, interacting, and content sharing with others.</Text>
		<Text Type="Financial Summary" lastModified="2017-06-29T09:08:06">BRIEF: For the three months ended 31 March 2017, Momo Inc (ADR) revenues increased from $50.9M to $265.2M. Net income increased from $7.1M to $81.2M. Revenues reflect Live video service increase from $15.6M to $212.6M, Mobile marketing increase of 45% to $17.9M, Mobile Games increase of 56% to $11.6M. Net income benefited from Interest Income increase from $1.7M to $3.8M (income), Share of income on equity method investm increase from $979K to $2.2M (earnings).</Text>
	</TextInfo>
	<contactInfo lastUpdated="2017-07-18T10:15:07">
		<streetAddress line="1">20th Floor, Block B, Tower 2</streetAddress>
		<streetAddress line="2">Wangjing SOHO, No.1 Futongdong Street</streetAddress>
		<streetAddress line="3">Chaoyang District</streetAddress>
		<city>BEIJING</city>
		<state-region>BEJ</state-region>
		<postalCode>100020</postalCode>
		<country code="CHN">China</country>
		<contactName></contactName>
		<contactTitle></contactTitle>
		<phone>
			<phone type="mainphone">
				<countryPhoneCode>86</countryPhoneCode>
				<city-areacode>10</city-areacode>
				<number>57310567</number>
			</phone>
		</phone>
	</contactInfo>
	<webLinks lastUpdated="2014-12-11T12:39:14"><webSite mainCategory="Home Page">http://www.immomo.com/</webSite><eMail mainCategory="Company Contact/E-mail"></eMail></webLinks>
	<peerInfo lastUpdated="2017-07-18T10:15:07">
		<IndustryInfo>
			<Industry type="TRBC" order="1" reported="0" code="5720102014" mnem="">Mobile Application Software</Industry>
			<Industry type="NAICS" order="1" reported="0" code="51121" mnem="">Software Publishers</Industry>
			<Industry type="SIC" order="1" reported="0" code="7372" mnem="">Prepackaged Software</Industry>
		</IndustryInfo>
	</peerInfo>
	<officers>
		<officer rank="1" since="07/2011">
			<firstName>Yan</firstName>
			<mI></mI>
			<lastName>Tang</lastName>
			<age>35 </age>
			<title startYear="2011" startMonth="07" startDay="" iD1="CHM" abbr1="Chmn." iD2="CEO" abbr2="CEO">Chairman of the Board, Chief Executive Officer</title>
		</officer>
		<officer rank="2" since="06/2014">
			<firstName>Xiaoliang</firstName>
			<mI></mI>
			<lastName>Lei</lastName>
			<age>31 </age>
			<title startYear="2014" startMonth="06" startDay="" iD1="CPR" abbr1="Co-Pres." iD2="" abbr2="">Co-President</title>
		</officer>
		<officer rank="3" since="03/2014">
			<firstName>Jingping</firstName>
			<mI></mI>
			<lastName>Zhang</lastName>
			<age>39 </age>
			<title startYear="2014" startMonth="03" startDay="" iD1="CPR" abbr1="Co-Pres." iD2="" abbr2="">Co-President</title>
		</officer>
		<officer rank="4" since="05/2014">
			<firstName>Xiaosong</firstName>
			<mI></mI>
			<lastName>Zhang</lastName>
			<age>51 </age>
			<title startYear="2014" startMonth="05" startDay="" iD1="CFO" abbr1="CFO" iD2="" abbr2="">Chief Financial Officer</title>
		</officer>
		<officer rank="5" since="06/2014">
			<firstName>Sichuan</firstName>
			<mI></mI>
			<lastName>Zhang</lastName>
			<age>31 </age>
			<title startYear="2014" startMonth="06" startDay="" iD1="CEX" abbr1="Corp. Exec." iD2="DRC" abbr2="Dir.">Director, President of U.S. operations</title>
		</officer>
		<officer rank="6" since="06/2014">
			<firstName>Li</firstName>
			<mI></mI>
			<lastName>Wang</lastName>
			<age>31 </age>
			<title startYear="2014" startMonth="06" startDay="" iD1="COO" abbr1="COO" iD2="" abbr2="">Chief Operating Officer</title>
		</officer>
		<officer rank="7" since="2014">
			<firstName>Zhiwei</firstName>
			<mI></mI>
			<lastName>Li</lastName>
			<age>28 </age>
			<title startYear="2014" startMonth="" startDay="" iD1="CTO" abbr1="CTO" iD2="" abbr2="">Chief Technology Officer</title>
		</officer>
	</officers>
	<Ratios PriceCurrency="USD" ReportingCurrency="USD" ExchangeRate="1.00000" LatestAvailableDate="2017-03-31">
		<Group ID="Price and Volume">
			<Ratio FieldName="NPRICE" Type="N">44.23000</Ratio>
			<Ratio FieldName="NHIG" Type="N">46.69000</Ratio>
			<Ratio FieldName="NLOW" Type="N">14.88000</Ratio>
			<Ratio FieldName="PDATE" Type="D">2017-08-15T00:00:00</Ratio>
			<Ratio FieldName="VOL10DAVG" Type="N">3.89038</Ratio>
			<Ratio FieldName="EV" Type="N">7861.70200</Ratio>
		</Group>
		<Group ID="Income Statement">
			<Ratio FieldName="MKTCAP" Type="N">8601.59500</Ratio>
			<Ratio FieldName="TTMREV" Type="N">767.41400</Ratio>
			<Ratio FieldName="TTMEBITD" Type="N">239.06500</Ratio>
			<Ratio FieldName="TTMNIAC" Type="N">219.40700</Ratio>
		</Group>
		<Group ID="Per share data">
			<Ratio FieldName="TTMEPSXCLX" Type="N">1.06832</Ratio>
			<Ratio FieldName="TTMREVPS" Type="N">3.75621</Ratio>
			<Ratio FieldName="QBVPS" Type="N">3.68895</Ratio>
			<Ratio FieldName="QCSHPS" Type="N">3.75283</Ratio>
			<Ratio FieldName="TTMCFSHR" Type="N">1.09242</Ratio>
			<Ratio FieldName="TTMDIVSHR" Type="N">0.00000</Ratio>
		</Group>
		<Group ID="Other Ratios">
			<Ratio FieldName="TTMGROSMGN" Type="N">55.47684</Ratio>
			<Ratio FieldName="TTMROEPCT" Type="N">36.29547</Ratio>
			<Ratio FieldName="TTMPR2REV" Type="N">11.20855</Ratio>
			<Ratio FieldName="PEEXCLXOR" Type="N">41.40145</Ratio>
			<Ratio FieldName="PRICE2BK" Type="N">11.98987</Ratio>
			<Ratio FieldName="Employees" Type="N">924</Ratio>
		</Group>
	</Ratios>
	<ForecastData ConsensusType="Mean" CurFiscalYear="2017" CurFiscalYearEndMonth="12" CurInterimEndCalYear="2017" CurInterimEndMonth="6" EarningsBasis="PRX">
		<Ratio FieldName="ConsRecom" Type="N">
			<Value PeriodType="CURR">1.5</Value>
		</Ratio>
		<Ratio FieldName="TargetPrice" Type="N">
			<Value PeriodType="CURR">49.25380</Value>
		</Ratio>
		<Ratio FieldName="ProjLTGrowthRate" Type="N">
			<Value PeriodType="CURR">49.9000</Value>
		</Ratio>
		<Ratio FieldName="ProjPE" Type="N">
			<Value PeriodType="CURR">28.15404</Value>
		</Ratio>
		<Ratio FieldName="ProjSales" Type="N">
			<Value PeriodType="CURR">1225.97750</Value>
		</Ratio>
		<Ratio FieldName="ProjSalesQ" Type="N">
			<Value PeriodType="CURR">286.33410</Value>
		</Ratio>
		<Ratio FieldName="ProjEPS" Type="N">
			<Value PeriodType="CURR">1.57100</Value>
		</Ratio>
		<Ratio FieldName="ProjEPSQ" Type="N">
			<Value PeriodType="CURR">0.30800</Value>
		</Ratio>
		<Ratio FieldName="ProjProfit" Type="N">
			<Value PeriodType="CURR">364.10600</Value>
		</Ratio>
		<Ratio FieldName="ProjDPS" Type="N">
			<Value PeriodType="CURR">0.00000</Value>
		</Ratio>
	</ForecastData>
</ReportSnapshot>
