<?xml version="1.0" encoding="UTF-8"?>
<ReportFinancialStatements Major="1" Minor="0" Revision="1">
<CoIDs>
<CoID Type="RepNo">0091N</CoID>
<CoID Type="CompanyName">Abbott Laboratories</CoID>
<CoID Type="IRSNo">360698440</CoID>
<CoID Type="CIKNo">0000001800</CoID>
</CoIDs>
<Issues>
<Issue ID="1" Type="C" Desc="Common Stock" Order="1">
<IssueID Type="Name">Ordinary Shares</IssueID>
<IssueID Type="Ticker">ABT</IssueID>
<IssueID Type="CUSIP">002824100</IssueID>
<IssueID Type="ISIN">US0028241000</IssueID>
<IssueID Type="RIC">ABT</IssueID>
<IssueID Type="SEDOL">2002305</IssueID>
<IssueID Type="DisplayRIC">ABT.N</IssueID>
<IssueID Type="InstrumentPI">258450</IssueID>
<IssueID Type="QuotePI">1089457</IssueID>
<Exchange Code="NYSE" Country="USA">New York Stock Exchange</Exchange>
<MostRecentSplit Date="1998-06-01">2.0</MostRecentSplit>
</Issue>
</Issues>
<CoGeneralInfo>
<CoStatus Code="1">Active</CoStatus>
<CoType Code="EQU">Equity Issue</CoType>
<LastModified>2017-08-04</LastModified>
<LatestAvailableAnnual>2016-12-31</LatestAvailableAnnual>
<LatestAvailableInterim>2017-06-30</LatestAvailableInterim>
<ReportingCurrency Code="USD">U.S. Dollars</ReportingCurrency>
<MostRecentExchange Date="2017-08-03">1.0</MostRecentExchange>
</CoGeneralInfo>
<StatementInfo>
<COAType Code="IND">Industry</COAType>
<BalanceSheetDisplay Code="CUR">Differentiates</BalanceSheetDisplay>
<CashFlowMethod Code="IND">Indirect</CashFlowMethod>
</StatementInfo>
<Notes>
<CFAAvailability Code="1" />
<IAvailability Code="1" />
<ISIAvailability Code="1" />
<BSIAvailability Code="1" />
<CFIAvailability Code="1" />
</Notes>
<FinancialStatements>
<COAMap>
<mapItem coaItem="SREV" statementType="INC" lineID="100" precision="1">Revenue</mapItem>
<mapItem coaItem="SORE" statementType="INC" lineID="300" precision="1">Other Revenue, Total</mapItem>
<mapItem coaItem="RTLR" statementType="INC" lineID="310" precision="1">Total Revenue</mapItem>
<mapItem coaItem="SCOR" statementType="INC" lineID="360" precision="1">Cost of Revenue, Total</mapItem>
<mapItem coaItem="SGRP" statementType="INC" lineID="370" precision="1">Gross Profit</mapItem>
<mapItem coaItem="SSGA" statementType="INC" lineID="550" precision="1">Selling/General/Admin. Expenses, Total</mapItem>
<mapItem coaItem="ERAD" statementType="INC" lineID="560" precision="1">Research &amp; Development</mapItem>
<mapItem coaItem="SDPR" statementType="INC" lineID="600" precision="1">Depreciation/Amortization</mapItem>
<mapItem coaItem="SINN" statementType="INC" lineID="671" precision="1">Interest Exp.(Inc.),Net-Operating, Total</mapItem>
<mapItem coaItem="SUIE" statementType="INC" lineID="740" precision="1">Unusual Expense (Income)</mapItem>
<mapItem coaItem="SOOE" statementType="INC" lineID="820" precision="1">Other Operating Expenses, Total</mapItem>
<mapItem coaItem="ETOE" statementType="INC" lineID="830" precision="1">Total Operating Expense</mapItem>
<mapItem coaItem="SOPI" statementType="INC" lineID="840" precision="1">Operating Income</mapItem>
<mapItem coaItem="SNIN" statementType="INC" lineID="911" precision="1">Interest Inc.(Exp.),Net-Non-Op., Total</mapItem>
<mapItem coaItem="NGLA" statementType="INC" lineID="920" precision="1">Gain (Loss) on Sale of Assets</mapItem>
<mapItem coaItem="SONT" statementType="INC" lineID="1270" precision="1">Other, Net</mapItem>
<mapItem coaItem="EIBT" statementType="INC" lineID="1280" precision="1">Net Income Before Taxes</mapItem>
<mapItem coaItem="TTAX" statementType="INC" lineID="1290" precision="1">Provision for Income Taxes</mapItem>
<mapItem coaItem="TIAT" statementType="INC" lineID="1300" precision="1">Net Income After Taxes</mapItem>
<mapItem coaItem="CMIN" statementType="INC" lineID="1310" precision="1">Minority Interest</mapItem>
<mapItem coaItem="CEIA" statementType="INC" lineID="1320" precision="1">Equity In Affiliates</mapItem>
<mapItem coaItem="CGAP" statementType="INC" lineID="1330" precision="1">U.S. GAAP Adjustment</mapItem>
<mapItem coaItem="NIBX" statementType="INC" lineID="1340" precision="1">Net Income Before Extra. Items</mapItem>
<mapItem coaItem="STXI" statementType="INC" lineID="1390" precision="1">Total Extraordinary Items</mapItem>
<mapItem coaItem="NINC" statementType="INC" lineID="1400" precision="1">Net Income</mapItem>
<mapItem coaItem="SANI" statementType="INC" lineID="1460" precision="1">Total Adjustments to Net Income</mapItem>
<mapItem coaItem="CIAC" statementType="INC" lineID="1470" precision="1">Income Available to Com Excl ExtraOrd</mapItem>
<mapItem coaItem="XNIC" statementType="INC" lineID="1480" precision="1">Income Available to Com Incl ExtraOrd</mapItem>
<mapItem coaItem="SDAJ" statementType="INC" lineID="1520" precision="1">Dilution Adjustment</mapItem>
<mapItem coaItem="SDNI" statementType="INC" lineID="1530" precision="1">Diluted Net Income</mapItem>
<mapItem coaItem="SDWS" statementType="INC" lineID="1540" precision="2">Diluted Weighted Average Shares</mapItem>
<mapItem coaItem="SDBF" statementType="INC" lineID="1550" precision="3">Diluted EPS Excluding ExtraOrd Items</mapItem>
<mapItem coaItem="DDPS1" statementType="INC" lineID="1570" precision="3">DPS - Common Stock Primary Issue</mapItem>
<mapItem coaItem="VDES" statementType="INC" lineID="1770" precision="3">Diluted Normalized EPS</mapItem>
<mapItem coaItem="ACSH" statementType="BAL" lineID="10" precision="1">Cash</mapItem>
<mapItem coaItem="ACAE" statementType="BAL" lineID="20" precision="1">Cash &amp; Equivalents</mapItem>
<mapItem coaItem="ASTI" statementType="BAL" lineID="30" precision="1">Short Term Investments</mapItem>
<mapItem coaItem="SCSI" statementType="BAL" lineID="40" precision="1">Cash and Short Term Investments</mapItem>
<mapItem coaItem="AACR" statementType="BAL" lineID="70" precision="1">Accounts Receivable - Trade, Net</mapItem>
<mapItem coaItem="ATRC" statementType="BAL" lineID="100" precision="1">Total Receivables, Net</mapItem>
<mapItem coaItem="AITL" statementType="BAL" lineID="180" precision="1">Total Inventory</mapItem>
<mapItem coaItem="APPY" statementType="BAL" lineID="190" precision="1">Prepaid Expenses</mapItem>
<mapItem coaItem="SOCA" statementType="BAL" lineID="260" precision="1">Other Current Assets, Total</mapItem>
<mapItem coaItem="ATCA" statementType="BAL" lineID="270" precision="1">Total Current Assets</mapItem>
<mapItem coaItem="APTC" statementType="BAL" lineID="520" precision="1">Property/Plant/Equipment, Total - Gross</mapItem>
<mapItem coaItem="ADEP" statementType="BAL" lineID="530" precision="1">Accumulated Depreciation, Total</mapItem>
<mapItem coaItem="APPN" statementType="BAL" lineID="540" precision="1">Property/Plant/Equipment, Total - Net</mapItem>
<mapItem coaItem="AGWI" statementType="BAL" lineID="570" precision="1">Goodwill, Net</mapItem>
<mapItem coaItem="AINT" statementType="BAL" lineID="600" precision="1">Intangibles, Net</mapItem>
<mapItem coaItem="SINV" statementType="BAL" lineID="690" precision="1">Long Term Investments</mapItem>
<mapItem coaItem="ALTR" statementType="BAL" lineID="710" precision="1">Note Receivable - Long Term</mapItem>
<mapItem coaItem="SOLA" statementType="BAL" lineID="780" precision="1">Other Long Term Assets, Total</mapItem>
<mapItem coaItem="ATOT" statementType="BAL" lineID="880" precision="1">Total Assets</mapItem>
<mapItem coaItem="LAPB" statementType="BAL" lineID="890" precision="1">Accounts Payable</mapItem>
<mapItem coaItem="LPBA" statementType="BAL" lineID="900" precision="1">Payable/Accrued</mapItem>
<mapItem coaItem="LAEX" statementType="BAL" lineID="910" precision="1">Accrued Expenses</mapItem>
<mapItem coaItem="LSTD" statementType="BAL" lineID="1120" precision="1">Notes Payable/Short Term Debt</mapItem>
<mapItem coaItem="LCLD" statementType="BAL" lineID="1130" precision="1">Current Port. of  LT Debt/Capital Leases</mapItem>
<mapItem coaItem="SOCL" statementType="BAL" lineID="1220" precision="1">Other Current liabilities, Total</mapItem>
<mapItem coaItem="LTCL" statementType="BAL" lineID="1230" precision="1">Total Current Liabilities</mapItem>
<mapItem coaItem="LLTD" statementType="BAL" lineID="1240" precision="1">Long Term Debt</mapItem>
<mapItem coaItem="LCLO" statementType="BAL" lineID="1250" precision="1">Capital Lease Obligations</mapItem>
<mapItem coaItem="LTTD" statementType="BAL" lineID="1260" precision="1">Total Long Term Debt</mapItem>
<mapItem coaItem="STLD" statementType="BAL" lineID="1270" precision="1">Total Debt</mapItem>
<mapItem coaItem="SBDT" statementType="BAL" lineID="1300" precision="1">Deferred Income Tax</mapItem>
<mapItem coaItem="LMIN" statementType="BAL" lineID="1310" precision="1">Minority Interest</mapItem>
<mapItem coaItem="SLTL" statementType="BAL" lineID="1370" precision="1">Other Liabilities, Total</mapItem>
<mapItem coaItem="LTLL" statementType="BAL" lineID="1380" precision="1">Total Liabilities</mapItem>
<mapItem coaItem="SRPR" statementType="BAL" lineID="1410" precision="1">Redeemable Preferred Stock, Total</mapItem>
<mapItem coaItem="SPRS" statementType="BAL" lineID="1460" precision="1">Preferred Stock - Non Redeemable, Net</mapItem>
<mapItem coaItem="SCMS" statementType="BAL" lineID="1490" precision="1">Common Stock, Total</mapItem>
<mapItem coaItem="QPIC" statementType="BAL" lineID="1500" precision="1">Additional Paid-In Capital</mapItem>
<mapItem coaItem="QRED" statementType="BAL" lineID="1510" precision="1">Retained Earnings (Accumulated Deficit)</mapItem>
<mapItem coaItem="QTSC" statementType="BAL" lineID="1520" precision="1">Treasury Stock - Common</mapItem>
<mapItem coaItem="QEDG" statementType="BAL" lineID="1530" precision="1">ESOP Debt Guarantee</mapItem>
<mapItem coaItem="QUGL" statementType="BAL" lineID="1540" precision="1">Unrealized Gain (Loss)</mapItem>
<mapItem coaItem="SOTE" statementType="BAL" lineID="1590" precision="1">Other Equity, Total</mapItem>
<mapItem coaItem="QTLE" statementType="BAL" lineID="1600" precision="1">Total Equity</mapItem>
<mapItem coaItem="QTEL" statementType="BAL" lineID="1610" precision="1">Total Liabilities &amp; Shareholders' Equity</mapItem>
<mapItem coaItem="QTCO" statementType="BAL" lineID="1660" precision="2">Total Common Shares Outstanding</mapItem>
<mapItem coaItem="QTPO" statementType="BAL" lineID="1770" precision="2">Total Preferred Shares Outstanding</mapItem>
<mapItem coaItem="STBP" statementType="BAL" lineID="1980" precision="3">Tangible Book Value per Share, Common Eq</mapItem>
<mapItem coaItem="ONET" statementType="CAS" lineID="10" precision="1">Net Income/Starting Line</mapItem>
<mapItem coaItem="SDED" statementType="CAS" lineID="40" precision="1">Depreciation/Depletion</mapItem>
<mapItem coaItem="SAMT" statementType="CAS" lineID="80" precision="1">Amortization</mapItem>
<mapItem coaItem="OBDT" statementType="CAS" lineID="90" precision="1">Deferred Taxes</mapItem>
<mapItem coaItem="SNCI" statementType="CAS" lineID="170" precision="1">Non-Cash Items</mapItem>
<mapItem coaItem="SOCF" statementType="CAS" lineID="470" precision="1">Changes in Working Capital</mapItem>
<mapItem coaItem="OTLO" statementType="CAS" lineID="480" precision="1">Cash from Operating Activities</mapItem>
<mapItem coaItem="SCEX" statementType="CAS" lineID="520" precision="1">Capital Expenditures</mapItem>
<mapItem coaItem="SICF" statementType="CAS" lineID="670" precision="1">Other Investing Cash Flow Items, Total</mapItem>
<mapItem coaItem="ITLI" statementType="CAS" lineID="680" precision="1">Cash from Investing Activities</mapItem>
<mapItem coaItem="SFCF" statementType="CAS" lineID="730" precision="1">Financing Cash Flow Items</mapItem>
<mapItem coaItem="FCDP" statementType="CAS" lineID="760" precision="1">Total Cash Dividends Paid</mapItem>
<mapItem coaItem="FPSS" statementType="CAS" lineID="880" precision="1">Issuance (Retirement) of Stock, Net</mapItem>
<mapItem coaItem="FPRD" statementType="CAS" lineID="970" precision="1">Issuance (Retirement) of Debt, Net</mapItem>
<mapItem coaItem="FTLF" statementType="CAS" lineID="980" precision="1">Cash from Financing Activities</mapItem>
<mapItem coaItem="SFEE" statementType="CAS" lineID="990" precision="1">Foreign Exchange Effects</mapItem>
<mapItem coaItem="SNCC" statementType="CAS" lineID="1000" precision="1">Net Change in Cash</mapItem>
<mapItem coaItem="SCIP" statementType="CAS" lineID="1040" precision="1">Cash Interest Paid</mapItem>
<mapItem coaItem="SCTP" statementType="CAS" lineID="1050" precision="1">Cash Taxes Paid</mapItem>
</COAMap>
<AnnualPeriods>
<FiscalPeriod Type="Annual" EndDate="2016-12-31" FiscalYear="2016">
<Statement Type="INC">
<FPHeader>
<PeriodLength>12</PeriodLength>
<periodType Code="M">Months</periodType>
<UpdateType Code="UPD">Updated Normal</UpdateType>
<AccountingStd></AccountingStd>
<StatementDate>2016-12-31</StatementDate>
<AuditorName Code="EY">Ernst &amp; Young LLP</AuditorName>
<AuditorOpinion Code="UNQ">Unqualified</AuditorOpinion>
<Source Date="2017-02-17">10-K</Source>
</FPHeader>
<lineItem coaCode="SREV">20853.000000</lineItem>
<lineItem coaCode="RTLR">20853.000000</lineItem>
<lineItem coaCode="SCOR">9015.000000</lineItem>
<lineItem coaCode="SGRP">11838.000000</lineItem>
<lineItem coaCode="SSGA">6653.000000</lineItem>
<lineItem coaCode="ERAD">1417.000000</lineItem>
<lineItem coaCode="SDPR">550.000000</lineItem>
<lineItem coaCode="SUIE">33.000000</lineItem>
<lineItem coaCode="ETOE">17668.000000</lineItem>
<lineItem coaCode="SOPI">3185.000000</lineItem>
<lineItem coaCode="SNIN">-827.000000</lineItem>
<lineItem coaCode="SONT">-945.000000</lineItem>
<lineItem coaCode="EIBT">1413.000000</lineItem>
<lineItem coaCode="TTAX">350.000000</lineItem>
<lineItem coaCode="TIAT">1063.000000</lineItem>
<lineItem coaCode="NIBX">1063.000000</lineItem>
<lineItem coaCode="STXI">337.000000</lineItem>
<lineItem coaCode="NINC">1400.000000</lineItem>
<lineItem coaCode="CIAC">1063.000000</lineItem>
<lineItem coaCode="XNIC">1400.000000</lineItem>
<lineItem coaCode="SDNI">1400.000000</lineItem>
<lineItem coaCode="SDWS">1483.000000</lineItem>
<lineItem coaCode="SDBF">0.716790</lineItem>
<lineItem coaCode="DDPS1">1.040000</lineItem>
<lineItem coaCode="VDES">0.733530</lineItem>
</Statement>
<Statement Type="BAL">
<FPHeader>
<UpdateType Code="UPD">Updated Normal</UpdateType>
<StatementDate>2016-12-31</StatementDate>
<AuditorName Code="EY">Ernst &amp; Young LLP</AuditorName>
<AuditorOpinion Code="UNQ">Unqualified</AuditorOpinion>
<Source Date="2017-02-17">10-K</Source>
</FPHeader>
<lineItem coaCode="ACAE">18620.000000</lineItem>
<lineItem coaCode="ASTI">155.000000</lineItem>
<lineItem coaCode="SCSI">18775.000000</lineItem>
<lineItem coaCode="AACR">3248.000000</lineItem>
<lineItem coaCode="ATRC">3248.000000</lineItem>
<lineItem coaCode="AITL">2434.000000</lineItem>
<lineItem coaCode="APPY">1530.000000</lineItem>
<lineItem coaCode="SOCA">789.000000</lineItem>
<lineItem coaCode="ATCA">26776.000000</lineItem>
<lineItem coaCode="APTC">12366.000000</lineItem>
<lineItem coaCode="ADEP">-6661.000000</lineItem>
<lineItem coaCode="APPN">5705.000000</lineItem>
<lineItem coaCode="AGWI">7683.000000</lineItem>
<lineItem coaCode="AINT">4539.000000</lineItem>
<lineItem coaCode="SINV">2947.000000</lineItem>
<lineItem coaCode="SOLA">5016.000000</lineItem>
<lineItem coaCode="ATOT">52666.000000</lineItem>
<lineItem coaCode="LAPB">1178.000000</lineItem>
<lineItem coaCode="LAEX">3251.000000</lineItem>
<lineItem coaCode="LSTD">868.000000</lineItem>
<lineItem coaCode="LCLD">3.000000</lineItem>
<lineItem coaCode="SOCL">1360.000000</lineItem>
<lineItem coaCode="LTCL">6660.000000</lineItem>
<lineItem coaCode="LLTD">20681.000000</lineItem>
<lineItem coaCode="LTTD">20681.000000</lineItem>
<lineItem coaCode="STLD">21552.000000</lineItem>
<lineItem coaCode="SBDT">356.000000</lineItem>
<lineItem coaCode="LMIN">179.000000</lineItem>
<lineItem coaCode="SLTL">4252.000000</lineItem>
<lineItem coaCode="LTLL">32128.000000</lineItem>
<lineItem coaCode="SCMS">13027.000000</lineItem>
<lineItem coaCode="QRED">25565.000000</lineItem>
<lineItem coaCode="QTSC">-10791.000000</lineItem>
<lineItem coaCode="QUGL">-69.000000</lineItem>
<lineItem coaCode="SOTE">-7194.000000</lineItem>
<lineItem coaCode="QTLE">20538.000000</lineItem>
<lineItem coaCode="QTEL">52666.000000</lineItem>
<lineItem coaCode="QTCO">1472.869210</lineItem>
<lineItem coaCode="STBP">5.646120</lineItem>
</Statement>
<Statement Type="CAS">
<FPHeader>
<PeriodLength>12</PeriodLength>
<periodType Code="M">Months</periodType>
<UpdateType Code="UPD">Updated Normal</UpdateType>
<StatementDate>2016-12-31</StatementDate>
<AuditorName Code="EY">Ernst &amp; Young LLP</AuditorName>
<AuditorOpinion Code="UNQ">Unqualified</AuditorOpinion>
<Source Date="2017-02-17">10-K</Source>
</FPHeader>
<lineItem coaCode="ONET">1400.000000</lineItem>
<lineItem coaCode="SDED">803.000000</lineItem>
<lineItem coaCode="SAMT">550.000000</lineItem>
<lineItem coaCode="SNCI">1963.000000</lineItem>
<lineItem coaCode="SCTP">620.000000</lineItem>
<lineItem coaCode="SCIP">181.000000</lineItem>
<lineItem coaCode="SOCF">-1513.000000</lineItem>
<lineItem coaCode="OTLO">3203.000000</lineItem>
<lineItem coaCode="SCEX">-1121.000000</lineItem>
<lineItem coaCode="SICF">873.000000</lineItem>
<lineItem coaCode="ITLI">-248.000000</lineItem>
<lineItem coaCode="SFCF">-195.000000</lineItem>
<lineItem coaCode="FCDP">-1539.000000</lineItem>
<lineItem coaCode="FPSS">-274.000000</lineItem>
<lineItem coaCode="FPRD">13155.000000</lineItem>
<lineItem coaCode="FTLF">11147.000000</lineItem>
<lineItem coaCode="SFEE">-483.000000</lineItem>
<lineItem coaCode="SNCC">13619.000000</lineItem>
</Statement>
</FiscalPeriod>
<FiscalPeriod Type="Annual" EndDate="2015-12-31" FiscalYear="2015">
<Statement Type="INC">
<FPHeader>
<PeriodLength>12</PeriodLength>
<periodType Code="M">Months</periodType>
<UpdateType Code="UPD">Updated Normal</UpdateType>
<AccountingStd></AccountingStd>
<StatementDate>2015-12-31</StatementDate>
<AuditorName Code="DHS">Deloitte &amp; Touche LLP</AuditorName>
<AuditorOpinion Code="UNQ">Unqualified</AuditorOpinion>
<Source Date="2016-02-19">10-K</Source>
</FPHeader>
<lineItem coaCode="SREV">20405.000000</lineItem>
<lineItem coaCode="RTLR">20405.000000</lineItem>
<lineItem coaCode="SCOR">8729.000000</lineItem>
<lineItem coaCode="SGRP">11676.000000</lineItem>
<lineItem coaCode="SSGA">6742.000000</lineItem>
<lineItem coaCode="ERAD">1371.000000</lineItem>
<lineItem coaCode="SDPR">601.000000</lineItem>
<lineItem coaCode="SUIE">95.000000</lineItem>
<lineItem coaCode="ETOE">17538.000000</lineItem>
<lineItem coaCode="SOPI">2867.000000</lineItem>
<lineItem coaCode="SNIN">35.000000</lineItem>
<lineItem coaCode="SONT">281.000000</lineItem>
<lineItem coaCode="EIBT">3183.000000</lineItem>
<lineItem coaCode="TTAX">577.000000</lineItem>
<lineItem coaCode="TIAT">2606.000000</lineItem>
<lineItem coaCode="NIBX">2606.000000</lineItem>
<lineItem coaCode="STXI">1817.000000</lineItem>
<lineItem coaCode="NINC">4423.000000</lineItem>
<lineItem coaCode="CIAC">2606.000000</lineItem>
<lineItem coaCode="XNIC">4423.000000</lineItem>
<lineItem coaCode="SDNI">4423.000000</lineItem>
<lineItem coaCode="SDWS">1506.000000</lineItem>
<lineItem coaCode="SDBF">1.730410</lineItem>
<lineItem coaCode="DDPS1">0.960000</lineItem>
<lineItem coaCode="VDES">1.782060</lineItem>
</Statement>
<Statement Type="BAL">
<FPHeader>
<UpdateType Code="UPD">Updated Normal</UpdateType>
<StatementDate>2015-12-31</StatementDate>
<AuditorName Code="DHS">Deloitte &amp; Touche LLP</AuditorName>
<AuditorOpinion Code="UNQ">Unqualified</AuditorOpinion>
<Source Date="2016-02-19">10-K</Source>
</FPHeader>
<lineItem coaCode="ACAE">5001.000000</lineItem>
<lineItem coaCode="ASTI">1124.000000</lineItem>
<lineItem coaCode="SCSI">6125.000000</lineItem>
<lineItem coaCode="AACR">3418.000000</lineItem>
<lineItem coaCode="ATRC">3418.000000</lineItem>
<lineItem coaCode="AITL">2599.000000</lineItem>
<lineItem coaCode="APPY">1908.000000</lineItem>
<lineItem coaCode="SOCA">105.000000</lineItem>
<lineItem coaCode="ATCA">14155.000000</lineItem>
<lineItem coaCode="APTC">12383.000000</lineItem>
<lineItem coaCode="ADEP">-6653.000000</lineItem>
<lineItem coaCode="APPN">5730.000000</lineItem>
<lineItem coaCode="AGWI">9638.000000</lineItem>
<lineItem coaCode="AINT">5562.000000</lineItem>
<lineItem coaCode="SINV">4041.000000</lineItem>
<lineItem coaCode="SOLA">2121.000000</lineItem>
<lineItem coaCode="ATOT">41247.000000</lineItem>
<lineItem coaCode="LAPB">1081.000000</lineItem>
<lineItem coaCode="LAEX">3771.000000</lineItem>
<lineItem coaCode="LSTD">2688.000000</lineItem>
<lineItem coaCode="LCLD">3.000000</lineItem>
<lineItem coaCode="SOCL">1643.000000</lineItem>
<lineItem coaCode="LTCL">9186.000000</lineItem>
<lineItem coaCode="LLTD">5871.000000</lineItem>
<lineItem coaCode="LTTD">5871.000000</lineItem>
<lineItem coaCode="STLD">8562.000000</lineItem>
<lineItem coaCode="SBDT">808.000000</lineItem>
<lineItem coaCode="LMIN">115.000000</lineItem>
<lineItem coaCode="SLTL">4056.000000</lineItem>
<lineItem coaCode="LTLL">20036.000000</lineItem>
<lineItem coaCode="SCMS">12734.000000</lineItem>
<lineItem coaCode="QRED">25757.000000</lineItem>
<lineItem coaCode="QTSC">-10622.000000</lineItem>
<lineItem coaCode="QUGL">65.000000</lineItem>
<lineItem coaCode="SOTE">-6723.000000</lineItem>
<lineItem coaCode="QTLE">21211.000000</lineItem>
<lineItem coaCode="QTEL">41247.000000</lineItem>
<lineItem coaCode="QTCO">1472.665050</lineItem>
<lineItem coaCode="STBP">4.081720</lineItem>
</Statement>
<Statement Type="CAS">
<FPHeader>
<PeriodLength>12</PeriodLength>
<periodType Code="M">Months</periodType>
<UpdateType Code="UPD">Updated Normal</UpdateType>
<StatementDate>2015-12-31</StatementDate>
<AuditorName Code="DHS">Deloitte &amp; Touche LLP</AuditorName>
<AuditorOpinion Code="UNQ">Unqualified</AuditorOpinion>
<Source Date="2016-02-19">10-K</Source>
</FPHeader>
<lineItem coaCode="ONET">4423.000000</lineItem>
<lineItem coaCode="SDED">871.000000</lineItem>
<lineItem coaCode="SAMT">601.000000</lineItem>
<lineItem coaCode="SNCI">-2773.000000</lineItem>
<lineItem coaCode="SCTP">631.000000</lineItem>
<lineItem coaCode="SCIP">166.000000</lineItem>
<lineItem coaCode="SOCF">-156.000000</lineItem>
<lineItem coaCode="OTLO">2966.000000</lineItem>
<lineItem coaCode="SCEX">-1110.000000</lineItem>
<lineItem coaCode="SICF">1516.000000</lineItem>
<lineItem coaCode="ITLI">406.000000</lineItem>
<lineItem coaCode="SFCF">-17.000000</lineItem>
<lineItem coaCode="FCDP">-1443.000000</lineItem>
<lineItem coaCode="FPSS">-1923.000000</lineItem>
<lineItem coaCode="FPRD">1147.000000</lineItem>
<lineItem coaCode="FTLF">-2236.000000</lineItem>
<lineItem coaCode="SFEE">-198.000000</lineItem>
<lineItem coaCode="SNCC">938.000000</lineItem>
</Statement>
</FiscalPeriod>
<FiscalPeriod Type="Annual" EndDate="2014-12-31" FiscalYear="2014">
<Statement Type="INC">
<FPHeader>
<PeriodLength>12</PeriodLength>
<periodType Code="M">Months</periodType>
<UpdateType Code="UPD">Updated Normal</UpdateType>
<AccountingStd></AccountingStd>
<StatementDate>2014-12-31</StatementDate>
<AuditorName Code="EY">Ernst &amp; Young LLP</AuditorName>
<AuditorOpinion Code="UNQ">Unqualified</AuditorOpinion>
<Source Date="2015-02-27">10-K</Source>
</FPHeader>
<lineItem coaCode="SREV">20247.000000</lineItem>
<lineItem coaCode="RTLR">20247.000000</lineItem>
<lineItem coaCode="SCOR">9198.000000</lineItem>
<lineItem coaCode="SGRP">11049.000000</lineItem>
<lineItem coaCode="SSGA">6439.000000</lineItem>
<lineItem coaCode="ERAD">1292.000000</lineItem>
<lineItem coaCode="SDPR">555.000000</lineItem>
<lineItem coaCode="SUIE">182.000000</lineItem>
<lineItem coaCode="ETOE">17666.000000</lineItem>
<lineItem coaCode="SOPI">2581.000000</lineItem>
<lineItem coaCode="SNIN">-49.000000</lineItem>
<lineItem coaCode="SONT">-14.000000</lineItem>
<lineItem coaCode="EIBT">2518.000000</lineItem>
<lineItem coaCode="TTAX">797.000000</lineItem>
<lineItem coaCode="TIAT">1721.000000</lineItem>
<lineItem coaCode="NIBX">1721.000000</lineItem>
<lineItem coaCode="STXI">563.000000</lineItem>
<lineItem coaCode="NINC">2284.000000</lineItem>
<lineItem coaCode="CIAC">1721.000000</lineItem>
<lineItem coaCode="XNIC">2284.000000</lineItem>
<lineItem coaCode="SDNI">2284.000000</lineItem>
<lineItem coaCode="SDWS">1527.000000</lineItem>
<lineItem coaCode="SDBF">1.127050</lineItem>
<lineItem coaCode="DDPS1">1.100000</lineItem>
<lineItem coaCode="VDES">1.208510</lineItem>
</Statement>
<Statement Type="BAL">
<FPHeader>
<UpdateType Code="RES">Restated Normal</UpdateType>
<StatementDate>2015-12-31</StatementDate>
<AuditorName Code="DHS">Deloitte &amp; Touche LLP</AuditorName>
<AuditorOpinion Code="UNQ">Unqualified</AuditorOpinion>
<Source Date="2016-02-19">10-K</Source>
</FPHeader>
<lineItem coaCode="ACAE">4063.000000</lineItem>
<lineItem coaCode="ASTI">397.000000</lineItem>
<lineItem coaCode="SCSI">4460.000000</lineItem>
<lineItem coaCode="AACR">3586.000000</lineItem>
<lineItem coaCode="ATRC">3586.000000</lineItem>
<lineItem coaCode="AITL">2643.000000</lineItem>
<lineItem coaCode="APPY">1975.000000</lineItem>
<lineItem coaCode="SOCA">892.000000</lineItem>
<lineItem coaCode="ATCA">13556.000000</lineItem>
<lineItem coaCode="APTC">12632.000000</lineItem>
<lineItem coaCode="ADEP">-6697.000000</lineItem>
<lineItem coaCode="APPN">5935.000000</lineItem>
<lineItem coaCode="AGWI">10067.000000</lineItem>
<lineItem coaCode="AINT">6198.000000</lineItem>
<lineItem coaCode="SINV">229.000000</lineItem>
<lineItem coaCode="SOLA">5222.000000</lineItem>
<lineItem coaCode="ATOT">41207.000000</lineItem>
<lineItem coaCode="LAPB">1064.000000</lineItem>
<lineItem coaCode="LAEX">3654.000000</lineItem>
<lineItem coaCode="LSTD">3937.000000</lineItem>
<lineItem coaCode="LCLD">55.000000</lineItem>
<lineItem coaCode="SOCL">1757.000000</lineItem>
<lineItem coaCode="LTCL">10467.000000</lineItem>
<lineItem coaCode="LLTD">3393.000000</lineItem>
<lineItem coaCode="LTTD">3393.000000</lineItem>
<lineItem coaCode="STLD">7385.000000</lineItem>
<lineItem coaCode="SBDT">872.000000</lineItem>
<lineItem coaCode="LMIN">113.000000</lineItem>
<lineItem coaCode="SLTL">4836.000000</lineItem>
<lineItem coaCode="LTLL">19681.000000</lineItem>
<lineItem coaCode="SCMS">12383.000000</lineItem>
<lineItem coaCode="QRED">22874.000000</lineItem>
<lineItem coaCode="QTSC">-8678.000000</lineItem>
<lineItem coaCode="QUGL">1.000000</lineItem>
<lineItem coaCode="SOTE">-5054.000000</lineItem>
<lineItem coaCode="QTLE">21526.000000</lineItem>
<lineItem coaCode="QTEL">41207.000000</lineItem>
<lineItem coaCode="QTCO">1515.122880</lineItem>
<lineItem coaCode="STBP">3.472330</lineItem>
</Statement>
<Statement Type="CAS">
<FPHeader>
<PeriodLength>12</PeriodLength>
<periodType Code="M">Months</periodType>
<UpdateType Code="UPD">Updated Normal</UpdateType>
<StatementDate>2014-12-31</StatementDate>
<AuditorName Code="EY">Ernst &amp; Young LLP</AuditorName>
<AuditorOpinion Code="UNQ">Unqualified</AuditorOpinion>
<Source Date="2015-02-27">10-K</Source>
</FPHeader>
<lineItem coaCode="ONET">2284.000000</lineItem>
<lineItem coaCode="SDED">918.000000</lineItem>
<lineItem coaCode="SAMT">630.000000</lineItem>
<lineItem coaCode="SNCI">333.000000</lineItem>
<lineItem coaCode="SCTP">448.000000</lineItem>
<lineItem coaCode="SCIP">182.000000</lineItem>
<lineItem coaCode="SOCF">-490.000000</lineItem>
<lineItem coaCode="OTLO">3675.000000</lineItem>
<lineItem coaCode="SCEX">-1077.000000</lineItem>
<lineItem coaCode="SICF">875.000000</lineItem>
<lineItem coaCode="ITLI">-202.000000</lineItem>
<lineItem coaCode="SFCF">-400.000000</lineItem>
<lineItem coaCode="FCDP">-1342.000000</lineItem>
<lineItem coaCode="FPSS">-1766.000000</lineItem>
<lineItem coaCode="FPRD">766.000000</lineItem>
<lineItem coaCode="FTLF">-2742.000000</lineItem>
<lineItem coaCode="SFEE">-143.000000</lineItem>
<lineItem coaCode="SNCC">588.000000</lineItem>
</Statement>
</FiscalPeriod>
<FiscalPeriod Type="Annual" EndDate="2013-12-31" FiscalYear="2013">
<Statement Type="INC">
<FPHeader>
<PeriodLength>12</PeriodLength>
<periodType Code="M">Months</periodType>
<UpdateType Code="RES">Restated Normal</UpdateType>
<AccountingStd></AccountingStd>
<StatementDate>2014-12-31</StatementDate>
<AuditorName Code="EY">Ernst &amp; Young LLP</AuditorName>
<AuditorOpinion Code="UNQ">Unqualified</AuditorOpinion>
<Source Date="2015-02-27">10-K</Source>
</FPHeader>
<lineItem coaCode="SREV">19657.000000</lineItem>
<lineItem coaCode="RTLR">19657.000000</lineItem>
<lineItem coaCode="SCOR">9193.000000</lineItem>
<lineItem coaCode="SGRP">10464.000000</lineItem>
<lineItem coaCode="SSGA">6372.000000</lineItem>
<lineItem coaCode="ERAD">1371.000000</lineItem>
<lineItem coaCode="SDPR">588.000000</lineItem>
<lineItem coaCode="SUIE">0.000000</lineItem>
<lineItem coaCode="ETOE">17524.000000</lineItem>
<lineItem coaCode="SOPI">2133.000000</lineItem>
<lineItem coaCode="SNIN">-124.000000</lineItem>
<lineItem coaCode="SONT">32.000000</lineItem>
<lineItem coaCode="EIBT">2041.000000</lineItem>
<lineItem coaCode="TTAX">53.000000</lineItem>
<lineItem coaCode="TIAT">1988.000000</lineItem>
<lineItem coaCode="NIBX">1988.000000</lineItem>
<lineItem coaCode="STXI">588.000000</lineItem>
<lineItem coaCode="NINC">2576.000000</lineItem>
<lineItem coaCode="CIAC">1988.000000</lineItem>
<lineItem coaCode="XNIC">2576.000000</lineItem>
<lineItem coaCode="SDNI">2576.000000</lineItem>
<lineItem coaCode="SDWS">1574.000000</lineItem>
<lineItem coaCode="SDBF">1.263020</lineItem>
<lineItem coaCode="DDPS1">0.560000</lineItem>
<lineItem coaCode="VDES">1.263020</lineItem>
</Statement>
<Statement Type="BAL">
<FPHeader>
<UpdateType Code="UPD">Updated Normal</UpdateType>
<StatementDate>2013-12-31</StatementDate>
<AuditorName Code="DHS">Deloitte &amp; Touche LLP</AuditorName>
<AuditorOpinion Code="UNQ">Unqualified</AuditorOpinion>
<Source Date="2014-02-21">10-K</Source>
</FPHeader>
<lineItem coaCode="ACAE">3475.000000</lineItem>
<lineItem coaCode="ASTI">4623.000000</lineItem>
<lineItem coaCode="SCSI">8098.000000</lineItem>
<lineItem coaCode="AACR">3986.000000</lineItem>
<lineItem coaCode="ATRC">3986.000000</lineItem>
<lineItem coaCode="AITL">2693.000000</lineItem>
<lineItem coaCode="APPY">1420.000000</lineItem>
<lineItem coaCode="SOCA">3050.000000</lineItem>
<lineItem coaCode="ATCA">19247.000000</lineItem>
<lineItem coaCode="APTC">12870.000000</lineItem>
<lineItem coaCode="ADEP">-6965.000000</lineItem>
<lineItem coaCode="APPN">5905.000000</lineItem>
<lineItem coaCode="AGWI">9772.000000</lineItem>
<lineItem coaCode="AINT">5735.000000</lineItem>
<lineItem coaCode="SINV">119.000000</lineItem>
<lineItem coaCode="SOLA">2175.000000</lineItem>
<lineItem coaCode="ATOT">42953.000000</lineItem>
<lineItem coaCode="LAPB">1026.000000</lineItem>
<lineItem coaCode="LAEX">4406.000000</lineItem>
<lineItem coaCode="LSTD">2659.000000</lineItem>
<lineItem coaCode="LCLD">9.000000</lineItem>
<lineItem coaCode="SOCL">1407.000000</lineItem>
<lineItem coaCode="LTCL">9507.000000</lineItem>
<lineItem coaCode="LLTD">3388.000000</lineItem>
<lineItem coaCode="LTTD">3388.000000</lineItem>
<lineItem coaCode="STLD">6056.000000</lineItem>
<lineItem coaCode="SBDT">466.000000</lineItem>
<lineItem coaCode="LMIN">96.000000</lineItem>
<lineItem coaCode="SLTL">4325.000000</lineItem>
<lineItem coaCode="LTLL">17782.000000</lineItem>
<lineItem coaCode="SCMS">12048.000000</lineItem>
<lineItem coaCode="QRED">21979.000000</lineItem>
<lineItem coaCode="QTSC">-6844.000000</lineItem>
<lineItem coaCode="QUGL">13.000000</lineItem>
<lineItem coaCode="SOTE">-2025.000000</lineItem>
<lineItem coaCode="QTLE">25171.000000</lineItem>
<lineItem coaCode="QTEL">42953.000000</lineItem>
<lineItem coaCode="QTCO">1548.098290</lineItem>
<lineItem coaCode="STBP">6.242500</lineItem>
</Statement>
<Statement Type="CAS">
<FPHeader>
<PeriodLength>12</PeriodLength>
<periodType Code="M">Months</periodType>
<UpdateType Code="UPD">Updated Normal</UpdateType>
<StatementDate>2013-12-31</StatementDate>
<AuditorName Code="DHS">Deloitte &amp; Touche LLP</AuditorName>
<AuditorOpinion Code="UNQ">Unqualified</AuditorOpinion>
<Source Date="2014-02-21">10-K</Source>
</FPHeader>
<lineItem coaCode="ONET">2576.000000</lineItem>
<lineItem coaCode="SDED">928.000000</lineItem>
<lineItem coaCode="SAMT">791.000000</lineItem>
<lineItem coaCode="SNCI">266.000000</lineItem>
<lineItem coaCode="SCTP">1039.000000</lineItem>
<lineItem coaCode="SCIP">148.000000</lineItem>
<lineItem coaCode="SOCF">-1237.000000</lineItem>
<lineItem coaCode="OTLO">3324.000000</lineItem>
<lineItem coaCode="SCEX">-1145.000000</lineItem>
<lineItem coaCode="SICF">-2784.000000</lineItem>
<lineItem coaCode="ITLI">-3929.000000</lineItem>
<lineItem coaCode="SFCF">-6396.000000</lineItem>
<lineItem coaCode="FCDP">-882.000000</lineItem>
<lineItem coaCode="FPSS">-1210.000000</lineItem>
<lineItem coaCode="FPRD">1792.000000</lineItem>
<lineItem coaCode="FTLF">-6696.000000</lineItem>
<lineItem coaCode="SFEE">-26.000000</lineItem>
<lineItem coaCode="SNCC">-7327.000000</lineItem>
</Statement>
</FiscalPeriod>
<FiscalPeriod Type="Annual" EndDate="2012-12-31" FiscalYear="2012">
<Statement Type="INC">
<FPHeader>
<PeriodLength>12</PeriodLength>
<periodType Code="M">Months</periodType>
<UpdateType Code="RES">Restated Normal</UpdateType>
<AccountingStd></AccountingStd>
<StatementDate>2014-12-31</StatementDate>
<AuditorName Code="EY">Ernst &amp; Young LLP</AuditorName>
<AuditorOpinion Code="UNQ">Unqualified</AuditorOpinion>
<Source Date="2015-02-27">10-K</Source>
</FPHeader>
<lineItem coaCode="SREV">19050.000000</lineItem>
<lineItem coaCode="RTLR">19050.000000</lineItem>
<lineItem coaCode="SCOR">8899.000000</lineItem>
<lineItem coaCode="SGRP">10151.000000</lineItem>
<lineItem coaCode="SSGA">6735.000000</lineItem>
<lineItem coaCode="ERAD">1461.000000</lineItem>
<lineItem coaCode="SDPR">595.000000</lineItem>
<lineItem coaCode="SUIE">1351.000000</lineItem>
<lineItem coaCode="ETOE">19041.000000</lineItem>
<lineItem coaCode="SOPI">9.000000</lineItem>
<lineItem coaCode="SNIN">-230.000000</lineItem>
<lineItem coaCode="SONT">1.000000</lineItem>
<lineItem coaCode="EIBT">-220.000000</lineItem>
<lineItem coaCode="TTAX">-457.000000</lineItem>
<lineItem coaCode="TIAT">237.000000</lineItem>
<lineItem coaCode="NIBX">237.000000</lineItem>
<lineItem coaCode="STXI">5726.000000</lineItem>
<lineItem coaCode="NINC">5963.000000</lineItem>
<lineItem coaCode="CIAC">237.000000</lineItem>
<lineItem coaCode="XNIC">5963.000000</lineItem>
<lineItem coaCode="SDNI">5963.000000</lineItem>
<lineItem coaCode="SDWS">1592.000000</lineItem>
<lineItem coaCode="SDBF">0.148870</lineItem>
<lineItem coaCode="DDPS1">2.010000</lineItem>
<lineItem coaCode="VDES">0.700470</lineItem>
</Statement>
<Statement Type="BAL">
<FPHeader>
<UpdateType Code="CLA">Reclassified Normal</UpdateType>
<StatementDate>2013-12-31</StatementDate>
<AuditorName Code="DHS">Deloitte &amp; Touche LLP</AuditorName>
<AuditorOpinion Code="UNQ">Unqualified</AuditorOpinion>
<Source Date="2014-02-21">10-K</Source>
</FPHeader>
<lineItem coaCode="ACAE">10802.000000</lineItem>
<lineItem coaCode="ASTI">4372.000000</lineItem>
<lineItem coaCode="SCSI">15174.000000</lineItem>
<lineItem coaCode="AACR">7613.000000</lineItem>
<lineItem coaCode="ATRC">7613.000000</lineItem>
<lineItem coaCode="AITL">3793.000000</lineItem>
<lineItem coaCode="APPY">1637.000000</lineItem>
<lineItem coaCode="SOCA">3106.000000</lineItem>
<lineItem coaCode="ATCA">31323.000000</lineItem>
<lineItem coaCode="APTC">18929.000000</lineItem>
<lineItem coaCode="ADEP">-10866.000000</lineItem>
<lineItem coaCode="APPN">8063.000000</lineItem>
<lineItem coaCode="AGWI">15774.000000</lineItem>
<lineItem coaCode="AINT">8588.000000</lineItem>
<lineItem coaCode="SINV">274.000000</lineItem>
<lineItem coaCode="SOLA">3213.000000</lineItem>
<lineItem coaCode="ATOT">67235.000000</lineItem>
<lineItem coaCode="LAPB">1797.000000</lineItem>
<lineItem coaCode="LAEX">8205.000000</lineItem>
<lineItem coaCode="LSTD">1467.000000</lineItem>
<lineItem coaCode="LCLD">309.000000</lineItem>
<lineItem coaCode="SOCL">1502.000000</lineItem>
<lineItem coaCode="LTCL">13280.000000</lineItem>
<lineItem coaCode="LLTD">18085.000000</lineItem>
<lineItem coaCode="LTTD">18085.000000</lineItem>
<lineItem coaCode="STLD">19861.000000</lineItem>
<lineItem coaCode="SBDT">710.000000</lineItem>
<lineItem coaCode="LMIN">92.000000</lineItem>
<lineItem coaCode="SLTL">8347.000000</lineItem>
<lineItem coaCode="LTLL">40514.000000</lineItem>
<lineItem coaCode="SCMS">11755.000000</lineItem>
<lineItem coaCode="QRED">24151.000000</lineItem>
<lineItem coaCode="QTSC">-5591.000000</lineItem>
<lineItem coaCode="QUGL">31.000000</lineItem>
<lineItem coaCode="SOTE">-3625.000000</lineItem>
<lineItem coaCode="QTLE">26721.000000</lineItem>
<lineItem coaCode="QTEL">67235.000000</lineItem>
<lineItem coaCode="QTCO">1576.667490</lineItem>
<lineItem coaCode="STBP">1.496190</lineItem>
</Statement>
<Statement Type="CAS">
<FPHeader>
<PeriodLength>12</PeriodLength>
<periodType Code="M">Months</periodType>
<UpdateType Code="CLA">Reclassified Normal</UpdateType>
<StatementDate>2013-12-31</StatementDate>
<AuditorName Code="DHS">Deloitte &amp; Touche LLP</AuditorName>
<AuditorOpinion Code="UNQ">Unqualified</AuditorOpinion>
<Source Date="2014-02-21">10-K</Source>
</FPHeader>
<lineItem coaCode="ONET">5963.000000</lineItem>
<lineItem coaCode="SDED">1363.000000</lineItem>
<lineItem coaCode="SAMT">1419.000000</lineItem>
<lineItem coaCode="SNCI">2428.000000</lineItem>
<lineItem coaCode="SCTP">1367.000000</lineItem>
<lineItem coaCode="SCIP">576.000000</lineItem>
<lineItem coaCode="SOCF">-1859.000000</lineItem>
<lineItem coaCode="OTLO">9314.000000</lineItem>
<lineItem coaCode="SCEX">-1795.000000</lineItem>
<lineItem coaCode="SICF">-3765.000000</lineItem>
<lineItem coaCode="ITLI">-5560.000000</lineItem>
<lineItem coaCode="SFCF">-521.000000</lineItem>
<lineItem coaCode="FCDP">-3183.000000</lineItem>
<lineItem coaCode="FPSS">-514.000000</lineItem>
<lineItem coaCode="FPRD">4413.000000</lineItem>
<lineItem coaCode="FTLF">195.000000</lineItem>
<lineItem coaCode="SFEE">40.000000</lineItem>
<lineItem coaCode="SNCC">3989.000000</lineItem>
</Statement>
</FiscalPeriod>
<FiscalPeriod Type="Annual" EndDate="2011-12-31" FiscalYear="2011">
<Statement Type="INC">
<FPHeader>
<PeriodLength>12</PeriodLength>
<periodType Code="M">Months</periodType>
<UpdateType Code="RES">Restated Normal</UpdateType>
<AccountingStd></AccountingStd>
<StatementDate>2013-12-31</StatementDate>
<AuditorName Code="DHS">Deloitte &amp; Touche LLP</AuditorName>
<AuditorOpinion Code="UNQ">Unqualified</AuditorOpinion>
<Source Date="2014-02-21">10-K</Source>
</FPHeader>
<lineItem coaCode="SREV">21407.000000</lineItem>
<lineItem coaCode="RTLR">21407.000000</lineItem>
<lineItem coaCode="SCOR">10061.000000</lineItem>
<lineItem coaCode="SGRP">11346.000000</lineItem>
<lineItem coaCode="SSGA">7365.000000</lineItem>
<lineItem coaCode="ERAD">1512.000000</lineItem>
<lineItem coaCode="SDPR">884.000000</lineItem>
<lineItem coaCode="SINN">-44.000000</lineItem>
<lineItem coaCode="SUIE">0.000000</lineItem>
<lineItem coaCode="ETOE">19778.000000</lineItem>
<lineItem coaCode="SOPI">1629.000000</lineItem>
<lineItem coaCode="SNIN">-274.000000</lineItem>
<lineItem coaCode="SONT">-119.000000</lineItem>
<lineItem coaCode="EIBT">1236.000000</lineItem>
<lineItem coaCode="TTAX">110.000000</lineItem>
<lineItem coaCode="TIAT">1126.000000</lineItem>
<lineItem coaCode="NIBX">1126.000000</lineItem>
<lineItem coaCode="STXI">3602.000000</lineItem>
<lineItem coaCode="NINC">4728.000000</lineItem>
<lineItem coaCode="CIAC">1126.000000</lineItem>
<lineItem coaCode="XNIC">4728.000000</lineItem>
<lineItem coaCode="SDNI">4728.000000</lineItem>
<lineItem coaCode="SDWS">1567.000000</lineItem>
<lineItem coaCode="SDBF">0.718570</lineItem>
<lineItem coaCode="DDPS1">1.880000</lineItem>
<lineItem coaCode="VDES">0.718570</lineItem>
</Statement>
<Statement Type="BAL">
<FPHeader>
<UpdateType Code="UPD">Updated Normal</UpdateType>
<StatementDate>2011-12-31</StatementDate>
<AuditorName Code="DHS">Deloitte &amp; Touche LLP</AuditorName>
<AuditorOpinion Code="UNQ">Unqualified</AuditorOpinion>
<Source Date="2012-02-21">10-K</Source>
</FPHeader>
<lineItem coaCode="ACAE">6812.820000</lineItem>
<lineItem coaCode="ASTI">1284.539000</lineItem>
<lineItem coaCode="SCSI">8097.359000</lineItem>
<lineItem coaCode="AACR">7683.920000</lineItem>
<lineItem coaCode="ATRC">7683.920000</lineItem>
<lineItem coaCode="AITL">3284.249000</lineItem>
<lineItem coaCode="APPY">2002.706000</lineItem>
<lineItem coaCode="SOCA">2700.540000</lineItem>
<lineItem coaCode="ATCA">23768.774000</lineItem>
<lineItem coaCode="APTC">18016.565000</lineItem>
<lineItem coaCode="ADEP">-10142.610000</lineItem>
<lineItem coaCode="APPN">7873.955000</lineItem>
<lineItem coaCode="AGWI">15705.380000</lineItem>
<lineItem coaCode="AINT">9989.636000</lineItem>
<lineItem coaCode="SINV">378.225000</lineItem>
<lineItem coaCode="ALTR">0.000000</lineItem>
<lineItem coaCode="SOLA">2560.923000</lineItem>
<lineItem coaCode="ATOT">60276.893000</lineItem>
<lineItem coaCode="LAPB">1721.127000</lineItem>
<lineItem coaCode="LAEX">9115.115000</lineItem>
<lineItem coaCode="LSTD">2347.859000</lineItem>
<lineItem coaCode="LCLD">1026.896000</lineItem>
<lineItem coaCode="SOCL">1269.231000</lineItem>
<lineItem coaCode="LTCL">15480.228000</lineItem>
<lineItem coaCode="LLTD">12039.822000</lineItem>
<lineItem coaCode="LTTD">12039.822000</lineItem>
<lineItem coaCode="STLD">15414.577000</lineItem>
<lineItem coaCode="SBDT">703.000000</lineItem>
<lineItem coaCode="LMIN">86.312000</lineItem>
<lineItem coaCode="SLTL">7527.698000</lineItem>
<lineItem coaCode="LTLL">35837.060000</lineItem>
<lineItem coaCode="SCMS">9817.134000</lineItem>
<lineItem coaCode="QRED">20907.362000</lineItem>
<lineItem coaCode="QTSC">-3687.478000</lineItem>
<lineItem coaCode="SOTE">-2597.185000</lineItem>
<lineItem coaCode="QTLE">24439.833000</lineItem>
<lineItem coaCode="QTEL">60276.893000</lineItem>
<lineItem coaCode="QTCO">1570.378820</lineItem>
<lineItem coaCode="STBP">-0.799290</lineItem>
</Statement>
<Statement Type="CAS">
<FPHeader>
<PeriodLength>12</PeriodLength>
<periodType Code="M">Months</periodType>
<UpdateType Code="CLA">Reclassified Normal</UpdateType>
<StatementDate>2013-12-31</StatementDate>
<AuditorName Code="DHS">Deloitte &amp; Touche LLP</AuditorName>
<AuditorOpinion Code="UNQ">Unqualified</AuditorOpinion>
<Source Date="2014-02-21">10-K</Source>
</FPHeader>
<lineItem coaCode="ONET">4728.000000</lineItem>
<lineItem coaCode="SDED">1395.000000</lineItem>
<lineItem coaCode="SAMT">1649.000000</lineItem>
<lineItem coaCode="SNCI">1197.000000</lineItem>
<lineItem coaCode="SCTP">1782.000000</lineItem>
<lineItem coaCode="SCIP">545.000000</lineItem>
<lineItem coaCode="SOCF">1.000000</lineItem>
<lineItem coaCode="OTLO">8970.000000</lineItem>
<lineItem coaCode="SCEX">-1491.000000</lineItem>
<lineItem coaCode="SICF">2152.000000</lineItem>
<lineItem coaCode="ITLI">661.000000</lineItem>
<lineItem coaCode="SFCF">-400.000000</lineItem>
<lineItem coaCode="FCDP">-2938.000000</lineItem>
<lineItem coaCode="FPSS">892.000000</lineItem>
<lineItem coaCode="FPRD">-3977.000000</lineItem>
<lineItem coaCode="FTLF">-6423.000000</lineItem>
<lineItem coaCode="SFEE">-43.000000</lineItem>
<lineItem coaCode="SNCC">3165.000000</lineItem>
</Statement>
</FiscalPeriod>
</AnnualPeriods>
<InterimPeriods>
<FiscalPeriod Type="Interim" EndDate="2017-06-30" FiscalYear="2017" FiscalPeriodNumber="2">
<Statement Type="INC">
<FPHeader>
<PeriodLength>3</PeriodLength>
<periodType Code="M">Months</periodType>
<UpdateType Code="UPD">Updated Normal</UpdateType>
<AccountingStd></AccountingStd>
<StatementDate>2017-06-30</StatementDate>
<Source Date="2017-08-02">10-Q</Source>
</FPHeader>
<lineItem coaCode="SREV">6637.000000</lineItem>
<lineItem coaCode="RTLR">6637.000000</lineItem>
<lineItem coaCode="SCOR">3173.000000</lineItem>
<lineItem coaCode="SGRP">3464.000000</lineItem>
<lineItem coaCode="SSGA">2132.000000</lineItem>
<lineItem coaCode="ERAD">513.000000</lineItem>
<lineItem coaCode="SDPR">392.000000</lineItem>
<lineItem coaCode="ETOE">6210.000000</lineItem>
<lineItem coaCode="SOPI">427.000000</lineItem>
<lineItem coaCode="SNIN">-171.000000</lineItem>
<lineItem coaCode="SONT">39.000000</lineItem>
<lineItem coaCode="EIBT">295.000000</lineItem>
<lineItem coaCode="TTAX">25.000000</lineItem>
<lineItem coaCode="TIAT">270.000000</lineItem>
<lineItem coaCode="NIBX">270.000000</lineItem>
<lineItem coaCode="STXI">13.000000</lineItem>
<lineItem coaCode="NINC">283.000000</lineItem>
<lineItem coaCode="CIAC">270.000000</lineItem>
<lineItem coaCode="XNIC">283.000000</lineItem>
<lineItem coaCode="SDNI">283.000000</lineItem>
<lineItem coaCode="SDWS">1740.524000</lineItem>
<lineItem coaCode="SDBF">0.155130</lineItem>
<lineItem coaCode="DDPS1">0.265000</lineItem>
<lineItem coaCode="VDES">0.155130</lineItem>
</Statement>
<Statement Type="BAL">
<FPHeader>
<UpdateType Code="UPD">Updated Normal</UpdateType>
<StatementDate>2017-06-30</StatementDate>
<Source Date="2017-08-02">10-Q</Source>
</FPHeader>
<lineItem coaCode="ACAE">9675.000000</lineItem>
<lineItem coaCode="ASTI">160.000000</lineItem>
<lineItem coaCode="SCSI">9835.000000</lineItem>
<lineItem coaCode="AACR">4633.000000</lineItem>
<lineItem coaCode="ATRC">4633.000000</lineItem>
<lineItem coaCode="AITL">3603.000000</lineItem>
<lineItem coaCode="APPY">1707.000000</lineItem>
<lineItem coaCode="SOCA">205.000000</lineItem>
<lineItem coaCode="ATCA">19983.000000</lineItem>
<lineItem coaCode="APTC">14476.000000</lineItem>
<lineItem coaCode="ADEP">-7190.000000</lineItem>
<lineItem coaCode="APPN">7286.000000</lineItem>
<lineItem coaCode="AGWI">22132.000000</lineItem>
<lineItem coaCode="AINT">18653.000000</lineItem>
<lineItem coaCode="SINV">1545.000000</lineItem>
<lineItem coaCode="SOLA">1552.000000</lineItem>
<lineItem coaCode="ATOT">71151.000000</lineItem>
<lineItem coaCode="LAPB">1667.000000</lineItem>
<lineItem coaCode="LAEX">4065.000000</lineItem>
<lineItem coaCode="LSTD">218.000000</lineItem>
<lineItem coaCode="LCLD">3.000000</lineItem>
<lineItem coaCode="SOCL">850.000000</lineItem>
<lineItem coaCode="LTCL">6803.000000</lineItem>
<lineItem coaCode="LLTD">23810.000000</lineItem>
<lineItem coaCode="LTTD">23810.000000</lineItem>
<lineItem coaCode="STLD">24031.000000</lineItem>
<lineItem coaCode="LMIN">186.000000</lineItem>
<lineItem coaCode="SLTL">8750.000000</lineItem>
<lineItem coaCode="LTLL">39549.000000</lineItem>
<lineItem coaCode="SCMS">23012.000000</lineItem>
<lineItem coaCode="QRED">25202.000000</lineItem>
<lineItem coaCode="QTSC">-10362.000000</lineItem>
<lineItem coaCode="QUGL">13.000000</lineItem>
<lineItem coaCode="SOTE">-6263.000000</lineItem>
<lineItem coaCode="QTLE">31602.000000</lineItem>
<lineItem coaCode="QTEL">71151.000000</lineItem>
<lineItem coaCode="QTCO">1737.443260</lineItem>
<lineItem coaCode="STBP">-5.285350</lineItem>
</Statement>
<Statement Type="CAS">
<FPHeader>
<PeriodLength>6</PeriodLength>
<periodType Code="M">Months</periodType>
<UpdateType Code="UPD">Updated Normal</UpdateType>
<StatementDate>2017-06-30</StatementDate>
<Source Date="2017-08-02">10-Q</Source>
</FPHeader>
<lineItem coaCode="ONET">702.000000</lineItem>
<lineItem coaCode="SDED">508.000000</lineItem>
<lineItem coaCode="SAMT">914.000000</lineItem>
<lineItem coaCode="SNCI">-16.000000</lineItem>
<lineItem coaCode="SOCF">-183.000000</lineItem>
<lineItem coaCode="OTLO">1925.000000</lineItem>
<lineItem coaCode="SCEX">-527.000000</lineItem>
<lineItem coaCode="SICF">-5633.000000</lineItem>
<lineItem coaCode="ITLI">-6160.000000</lineItem>
<lineItem coaCode="SFCF">-13.000000</lineItem>
<lineItem coaCode="FCDP">-922.000000</lineItem>
<lineItem coaCode="FPSS">88.000000</lineItem>
<lineItem coaCode="FPRD">-3936.000000</lineItem>
<lineItem coaCode="FTLF">-4783.000000</lineItem>
<lineItem coaCode="SFEE">73.000000</lineItem>
<lineItem coaCode="SNCC">-8945.000000</lineItem>
</Statement>
</FiscalPeriod>
<FiscalPeriod Type="Interim" EndDate="2017-03-31" FiscalYear="2017" FiscalPeriodNumber="1">
<Statement Type="INC">
<FPHeader>
<PeriodLength>3</PeriodLength>
<periodType Code="M">Months</periodType>
<UpdateType Code="UPD">Updated Normal</UpdateType>
<AccountingStd></AccountingStd>
<StatementDate>2017-03-31</StatementDate>
<Source Date="2017-05-03">10-Q</Source>
</FPHeader>
<lineItem coaCode="SREV">6335.000000</lineItem>
<lineItem coaCode="RTLR">6335.000000</lineItem>
<lineItem coaCode="SCOR">3044.000000</lineItem>
<lineItem coaCode="SGRP">3291.000000</lineItem>
<lineItem coaCode="SSGA">2299.000000</lineItem>
<lineItem coaCode="ERAD">541.000000</lineItem>
<lineItem coaCode="SDPR">522.000000</lineItem>
<lineItem coaCode="SUIE">131.000000</lineItem>
<lineItem coaCode="ETOE">6537.000000</lineItem>
<lineItem coaCode="SOPI">-202.000000</lineItem>
<lineItem coaCode="SNIN">-188.000000</lineItem>
<lineItem coaCode="SONT">1126.000000</lineItem>
<lineItem coaCode="EIBT">736.000000</lineItem>
<lineItem coaCode="TTAX">350.000000</lineItem>
<lineItem coaCode="TIAT">386.000000</lineItem>
<lineItem coaCode="NIBX">386.000000</lineItem>
<lineItem coaCode="STXI">33.000000</lineItem>
<lineItem coaCode="NINC">419.000000</lineItem>
<lineItem coaCode="CIAC">386.000000</lineItem>
<lineItem coaCode="XNIC">419.000000</lineItem>
<lineItem coaCode="SDNI">419.000000</lineItem>
<lineItem coaCode="SDWS">1735.195000</lineItem>
<lineItem coaCode="SDBF">0.222450</lineItem>
<lineItem coaCode="DDPS1">0.265000</lineItem>
<lineItem coaCode="VDES">0.262050</lineItem>
</Statement>
<Statement Type="BAL">
<FPHeader>
<UpdateType Code="UPD">Updated Normal</UpdateType>
<StatementDate>2017-03-31</StatementDate>
<Source Date="2017-05-03">10-Q</Source>
</FPHeader>
<lineItem coaCode="ACAE">8706.000000</lineItem>
<lineItem coaCode="ASTI">154.000000</lineItem>
<lineItem coaCode="SCSI">8860.000000</lineItem>
<lineItem coaCode="AACR">4510.000000</lineItem>
<lineItem coaCode="ATRC">4510.000000</lineItem>
<lineItem coaCode="AITL">3995.000000</lineItem>
<lineItem coaCode="APPY">1723.000000</lineItem>
<lineItem coaCode="SOCA">241.000000</lineItem>
<lineItem coaCode="ATCA">19329.000000</lineItem>
<lineItem coaCode="APTC">14172.000000</lineItem>
<lineItem coaCode="ADEP">-6907.000000</lineItem>
<lineItem coaCode="APPN">7265.000000</lineItem>
<lineItem coaCode="AGWI">21353.000000</lineItem>
<lineItem coaCode="AINT">19405.000000</lineItem>
<lineItem coaCode="SINV">1756.000000</lineItem>
<lineItem coaCode="SOLA">1779.000000</lineItem>
<lineItem coaCode="ATOT">70887.000000</lineItem>
<lineItem coaCode="LAPB">1481.000000</lineItem>
<lineItem coaCode="LAEX">4200.000000</lineItem>
<lineItem coaCode="LSTD">207.000000</lineItem>
<lineItem coaCode="LCLD">3.000000</lineItem>
<lineItem coaCode="SOCL">755.000000</lineItem>
<lineItem coaCode="LTCL">6646.000000</lineItem>
<lineItem coaCode="LLTD">23764.000000</lineItem>
<lineItem coaCode="LTTD">23764.000000</lineItem>
<lineItem coaCode="STLD">23974.000000</lineItem>
<lineItem coaCode="LMIN">185.000000</lineItem>
<lineItem coaCode="SLTL">8930.000000</lineItem>
<lineItem coaCode="LTLL">39525.000000</lineItem>
<lineItem coaCode="SCMS">22886.000000</lineItem>
<lineItem coaCode="QRED">25387.000000</lineItem>
<lineItem coaCode="QTSC">-10379.000000</lineItem>
<lineItem coaCode="QUGL">11.000000</lineItem>
<lineItem coaCode="SOTE">-6543.000000</lineItem>
<lineItem coaCode="QTLE">31362.000000</lineItem>
<lineItem coaCode="QTEL">70887.000000</lineItem>
<lineItem coaCode="QTCO">1735.272050</lineItem>
<lineItem coaCode="STBP">-5.414710</lineItem>
</Statement>
<Statement Type="CAS">
<FPHeader>
<PeriodLength>3</PeriodLength>
<periodType Code="M">Months</periodType>
<UpdateType Code="UPD">Updated Normal</UpdateType>
<StatementDate>2017-03-31</StatementDate>
<Source Date="2017-05-03">10-Q</Source>
</FPHeader>
<lineItem coaCode="ONET">419.000000</lineItem>
<lineItem coaCode="SDED">252.000000</lineItem>
<lineItem coaCode="SAMT">522.000000</lineItem>
<lineItem coaCode="SNCI">-487.000000</lineItem>
<lineItem coaCode="SOCF">-132.000000</lineItem>
<lineItem coaCode="OTLO">574.000000</lineItem>
<lineItem coaCode="SCEX">-272.000000</lineItem>
<lineItem coaCode="SICF">-5882.000000</lineItem>
<lineItem coaCode="ITLI">-6154.000000</lineItem>
<lineItem coaCode="SFCF">-13.000000</lineItem>
<lineItem coaCode="FCDP">-460.000000</lineItem>
<lineItem coaCode="FPSS">34.000000</lineItem>
<lineItem coaCode="FPRD">-3960.000000</lineItem>
<lineItem coaCode="FTLF">-4399.000000</lineItem>
<lineItem coaCode="SFEE">65.000000</lineItem>
<lineItem coaCode="SNCC">-9914.000000</lineItem>
</Statement>
</FiscalPeriod>
<FiscalPeriod Type="Interim" EndDate="2016-12-31" FiscalYear="2016" FiscalPeriodNumber="4">
<Statement Type="INC">
<FPHeader>
<PeriodLength>3</PeriodLength>
<periodType Code="M">Months</periodType>
<UpdateType Code="UCA">Updated Calculated</UpdateType>
<AccountingStd></AccountingStd>
<StatementDate>2016-12-31</StatementDate>
<AuditorName Code="EY">Ernst &amp; Young LLP</AuditorName>
<AuditorOpinion Code="UNQ">Unqualified</AuditorOpinion>
<Source Date="2017-02-17">10-K</Source>
</FPHeader>
<lineItem coaCode="SREV">5333.000000</lineItem>
<lineItem coaCode="RTLR">5333.000000</lineItem>
<lineItem coaCode="SCOR">2310.000000</lineItem>
<lineItem coaCode="SGRP">3023.000000</lineItem>
<lineItem coaCode="SSGA">1606.000000</lineItem>
<lineItem coaCode="ERAD">338.000000</lineItem>
<lineItem coaCode="SDPR">121.000000</lineItem>
<lineItem coaCode="SUIE">10.000000</lineItem>
<lineItem coaCode="ETOE">4385.000000</lineItem>
<lineItem coaCode="SOPI">948.000000</lineItem>
<lineItem coaCode="SNIN">-127.000000</lineItem>
<lineItem coaCode="SONT">54.000000</lineItem>
<lineItem coaCode="EIBT">875.000000</lineItem>
<lineItem coaCode="TTAX">110.000000</lineItem>
<lineItem coaCode="TIAT">765.000000</lineItem>
<lineItem coaCode="NIBX">765.000000</lineItem>
<lineItem coaCode="STXI">33.000000</lineItem>
<lineItem coaCode="NINC">798.000000</lineItem>
<lineItem coaCode="CIAC">765.000000</lineItem>
<lineItem coaCode="XNIC">798.000000</lineItem>
<lineItem coaCode="SDNI">798.000000</lineItem>
<lineItem coaCode="SDWS">1483.960000</lineItem>
<lineItem coaCode="SDBF">0.515510</lineItem>
<lineItem coaCode="DDPS1">0.260000</lineItem>
<lineItem coaCode="VDES">0.521400</lineItem>
</Statement>
<Statement Type="BAL">
<FPHeader>
<UpdateType Code="UPD">Updated Normal</UpdateType>
<StatementDate>2016-12-31</StatementDate>
<AuditorName Code="EY">Ernst &amp; Young LLP</AuditorName>
<AuditorOpinion Code="UNQ">Unqualified</AuditorOpinion>
<Source Date="2017-02-17">10-K</Source>
</FPHeader>
<lineItem coaCode="ACAE">18620.000000</lineItem>
<lineItem coaCode="ASTI">155.000000</lineItem>
<lineItem coaCode="SCSI">18775.000000</lineItem>
<lineItem coaCode="AACR">3248.000000</lineItem>
<lineItem coaCode="ATRC">3248.000000</lineItem>
<lineItem coaCode="AITL">2434.000000</lineItem>
<lineItem coaCode="APPY">1530.000000</lineItem>
<lineItem coaCode="SOCA">789.000000</lineItem>
<lineItem coaCode="ATCA">26776.000000</lineItem>
<lineItem coaCode="APTC">12366.000000</lineItem>
<lineItem coaCode="ADEP">-6661.000000</lineItem>
<lineItem coaCode="APPN">5705.000000</lineItem>
<lineItem coaCode="AGWI">7683.000000</lineItem>
<lineItem coaCode="AINT">4539.000000</lineItem>
<lineItem coaCode="SINV">2947.000000</lineItem>
<lineItem coaCode="SOLA">5016.000000</lineItem>
<lineItem coaCode="ATOT">52666.000000</lineItem>
<lineItem coaCode="LAPB">1178.000000</lineItem>
<lineItem coaCode="LAEX">3251.000000</lineItem>
<lineItem coaCode="LSTD">868.000000</lineItem>
<lineItem coaCode="LCLD">3.000000</lineItem>
<lineItem coaCode="SOCL">1360.000000</lineItem>
<lineItem coaCode="LTCL">6660.000000</lineItem>
<lineItem coaCode="LLTD">20681.000000</lineItem>
<lineItem coaCode="LTTD">20681.000000</lineItem>
<lineItem coaCode="STLD">21552.000000</lineItem>
<lineItem coaCode="LMIN">179.000000</lineItem>
<lineItem coaCode="SLTL">4608.000000</lineItem>
<lineItem coaCode="LTLL">32128.000000</lineItem>
<lineItem coaCode="SCMS">13027.000000</lineItem>
<lineItem coaCode="QRED">25565.000000</lineItem>
<lineItem coaCode="QTSC">-10791.000000</lineItem>
<lineItem coaCode="QUGL">-69.000000</lineItem>
<lineItem coaCode="SOTE">-7194.000000</lineItem>
<lineItem coaCode="QTLE">20538.000000</lineItem>
<lineItem coaCode="QTEL">52666.000000</lineItem>
<lineItem coaCode="QTCO">1472.869210</lineItem>
<lineItem coaCode="STBP">5.646120</lineItem>
</Statement>
<Statement Type="CAS">
<FPHeader>
<PeriodLength>12</PeriodLength>
<periodType Code="M">Months</periodType>
<UpdateType Code="UPD">Updated Normal</UpdateType>
<StatementDate>2016-12-31</StatementDate>
<AuditorName Code="EY">Ernst &amp; Young LLP</AuditorName>
<AuditorOpinion Code="UNQ">Unqualified</AuditorOpinion>
<Source Date="2017-02-17">10-K</Source>
</FPHeader>
<lineItem coaCode="ONET">1400.000000</lineItem>
<lineItem coaCode="SDED">803.000000</lineItem>
<lineItem coaCode="SAMT">550.000000</lineItem>
<lineItem coaCode="SNCI">1963.000000</lineItem>
<lineItem coaCode="SCTP">620.000000</lineItem>
<lineItem coaCode="SCIP">181.000000</lineItem>
<lineItem coaCode="SOCF">-1513.000000</lineItem>
<lineItem coaCode="OTLO">3203.000000</lineItem>
<lineItem coaCode="SCEX">-1121.000000</lineItem>
<lineItem coaCode="SICF">873.000000</lineItem>
<lineItem coaCode="ITLI">-248.000000</lineItem>
<lineItem coaCode="SFCF">-195.000000</lineItem>
<lineItem coaCode="FCDP">-1539.000000</lineItem>
<lineItem coaCode="FPSS">-274.000000</lineItem>
<lineItem coaCode="FPRD">13155.000000</lineItem>
<lineItem coaCode="FTLF">11147.000000</lineItem>
<lineItem coaCode="SFEE">-483.000000</lineItem>
<lineItem coaCode="SNCC">13619.000000</lineItem>
</Statement>
</FiscalPeriod>
<FiscalPeriod Type="Interim" EndDate="2016-09-30" FiscalYear="2016" FiscalPeriodNumber="3">
<Statement Type="INC">
<FPHeader>
<PeriodLength>3</PeriodLength>
<periodType Code="M">Months</periodType>
<UpdateType Code="UPD">Updated Normal</UpdateType>
<AccountingStd></AccountingStd>
<StatementDate>2016-09-30</StatementDate>
<Source Date="2016-11-03">10-Q</Source>
</FPHeader>
<lineItem coaCode="SREV">5302.000000</lineItem>
<lineItem coaCode="RTLR">5302.000000</lineItem>
<lineItem coaCode="SCOR">2285.000000</lineItem>
<lineItem coaCode="SGRP">3017.000000</lineItem>
<lineItem coaCode="SSGA">1618.000000</lineItem>
<lineItem coaCode="ERAD">352.000000</lineItem>
<lineItem coaCode="SDPR">140.000000</lineItem>
<lineItem coaCode="SUIE">10.000000</lineItem>
<lineItem coaCode="ETOE">4405.000000</lineItem>
<lineItem coaCode="SOPI">897.000000</lineItem>
<lineItem coaCode="SNIN">-104.000000</lineItem>
<lineItem coaCode="SONT">-972.000000</lineItem>
<lineItem coaCode="EIBT">-179.000000</lineItem>
<lineItem coaCode="TTAX">178.000000</lineItem>
<lineItem coaCode="TIAT">-357.000000</lineItem>
<lineItem coaCode="NIBX">-357.000000</lineItem>
<lineItem coaCode="STXI">28.000000</lineItem>
<lineItem coaCode="NINC">-329.000000</lineItem>
<lineItem coaCode="CIAC">-357.000000</lineItem>
<lineItem coaCode="XNIC">-329.000000</lineItem>
<lineItem coaCode="SDAJ">0.000000</lineItem>
<lineItem coaCode="SDNI">-329.000000</lineItem>
<lineItem coaCode="SDWS">1476.366000</lineItem>
<lineItem coaCode="SDBF">-0.241810</lineItem>
<lineItem coaCode="DDPS1">0.260000</lineItem>
<lineItem coaCode="VDES">-0.237410</lineItem>
</Statement>
<Statement Type="BAL">
<FPHeader>
<UpdateType Code="UPD">Updated Normal</UpdateType>
<StatementDate>2016-09-30</StatementDate>
<Source Date="2016-11-03">10-Q</Source>
</FPHeader>
<lineItem coaCode="ACAE">2500.000000</lineItem>
<lineItem coaCode="ASTI">2007.000000</lineItem>
<lineItem coaCode="SCSI">4507.000000</lineItem>
<lineItem coaCode="AACR">3320.000000</lineItem>
<lineItem coaCode="ATRC">3320.000000</lineItem>
<lineItem coaCode="AITL">2613.000000</lineItem>
<lineItem coaCode="APPY">1836.000000</lineItem>
<lineItem coaCode="SOCA">702.000000</lineItem>
<lineItem coaCode="ATCA">12978.000000</lineItem>
<lineItem coaCode="APTC">12452.000000</lineItem>
<lineItem coaCode="ADEP">-6718.000000</lineItem>
<lineItem coaCode="APPN">5734.000000</lineItem>
<lineItem coaCode="AGWI">7812.000000</lineItem>
<lineItem coaCode="AINT">4674.000000</lineItem>
<lineItem coaCode="SINV">2997.000000</lineItem>
<lineItem coaCode="SOLA">5302.000000</lineItem>
<lineItem coaCode="ATOT">39497.000000</lineItem>
<lineItem coaCode="LAPB">1051.000000</lineItem>
<lineItem coaCode="LAEX">3358.000000</lineItem>
<lineItem coaCode="LSTD">2009.000000</lineItem>
<lineItem coaCode="LCLD">4.000000</lineItem>
<lineItem coaCode="SOCL">1899.000000</lineItem>
<lineItem coaCode="LTCL">8321.000000</lineItem>
<lineItem coaCode="LLTD">5975.000000</lineItem>
<lineItem coaCode="LTTD">5975.000000</lineItem>
<lineItem coaCode="STLD">7988.000000</lineItem>
<lineItem coaCode="LMIN">120.000000</lineItem>
<lineItem coaCode="SLTL">4305.000000</lineItem>
<lineItem coaCode="LTLL">18721.000000</lineItem>
<lineItem coaCode="SCMS">12939.000000</lineItem>
<lineItem coaCode="QRED">25162.000000</lineItem>
<lineItem coaCode="QTSC">-10792.000000</lineItem>
<lineItem coaCode="QUGL">-78.000000</lineItem>
<lineItem coaCode="SOTE">-6455.000000</lineItem>
<lineItem coaCode="QTLE">20776.000000</lineItem>
<lineItem coaCode="QTEL">39497.000000</lineItem>
<lineItem coaCode="QTCO">1472.309520</lineItem>
<lineItem coaCode="STBP">5.630610</lineItem>
</Statement>
<Statement Type="CAS">
<FPHeader>
<PeriodLength>9</PeriodLength>
<periodType Code="M">Months</periodType>
<UpdateType Code="UPD">Updated Normal</UpdateType>
<StatementDate>2016-09-30</StatementDate>
<Source Date="2016-11-03">10-Q</Source>
</FPHeader>
<lineItem coaCode="ONET">602.000000</lineItem>
<lineItem coaCode="SDED">605.000000</lineItem>
<lineItem coaCode="SAMT">429.000000</lineItem>
<lineItem coaCode="SNCI">665.000000</lineItem>
<lineItem coaCode="SOCF">-268.000000</lineItem>
<lineItem coaCode="OTLO">2033.000000</lineItem>
<lineItem coaCode="SCEX">-802.000000</lineItem>
<lineItem coaCode="SICF">-996.000000</lineItem>
<lineItem coaCode="ITLI">-1798.000000</lineItem>
<lineItem coaCode="SFCF">-195.000000</lineItem>
<lineItem coaCode="FCDP">-1153.000000</lineItem>
<lineItem coaCode="FPSS">-316.000000</lineItem>
<lineItem coaCode="FPRD">-693.000000</lineItem>
<lineItem coaCode="FTLF">-2357.000000</lineItem>
<lineItem coaCode="SFEE">-379.000000</lineItem>
<lineItem coaCode="SNCC">-2501.000000</lineItem>
</Statement>
</FiscalPeriod>
<FiscalPeriod Type="Interim" EndDate="2016-06-30" FiscalYear="2016" FiscalPeriodNumber="2">
<Statement Type="INC">
<FPHeader>
<PeriodLength>3</PeriodLength>
<periodType Code="M">Months</periodType>
<UpdateType Code="UPD">Updated Normal</UpdateType>
<AccountingStd></AccountingStd>
<StatementDate>2016-06-30</StatementDate>
<Source Date="2016-08-03">10-Q</Source>
</FPHeader>
<lineItem coaCode="SREV">5333.000000</lineItem>
<lineItem coaCode="RTLR">5333.000000</lineItem>
<lineItem coaCode="SCOR">2281.000000</lineItem>
<lineItem coaCode="SGRP">3052.000000</lineItem>
<lineItem coaCode="SSGA">1746.000000</lineItem>
<lineItem coaCode="ERAD">348.000000</lineItem>
<lineItem coaCode="SDPR">145.000000</lineItem>
<lineItem coaCode="SUIE">-3.000000</lineItem>
<lineItem coaCode="ETOE">4517.000000</lineItem>
<lineItem coaCode="SOPI">816.000000</lineItem>
<lineItem coaCode="SNIN">-93.000000</lineItem>
<lineItem coaCode="SONT">-8.000000</lineItem>
<lineItem coaCode="EIBT">715.000000</lineItem>
<lineItem coaCode="TTAX">116.000000</lineItem>
<lineItem coaCode="TIAT">599.000000</lineItem>
<lineItem coaCode="NIBX">599.000000</lineItem>
<lineItem coaCode="STXI">16.000000</lineItem>
<lineItem coaCode="NINC">615.000000</lineItem>
<lineItem coaCode="CIAC">599.000000</lineItem>
<lineItem coaCode="XNIC">615.000000</lineItem>
<lineItem coaCode="SDAJ">0.000000</lineItem>
<lineItem coaCode="SDNI">615.000000</lineItem>
<lineItem coaCode="SDWS">1480.492000</lineItem>
<lineItem coaCode="SDBF">0.404600</lineItem>
<lineItem coaCode="DDPS1">0.260000</lineItem>
<lineItem coaCode="VDES">0.402900</lineItem>
</Statement>
<Statement Type="BAL">
<FPHeader>
<UpdateType Code="UPD">Updated Normal</UpdateType>
<StatementDate>2016-06-30</StatementDate>
<Source Date="2016-08-03">10-Q</Source>
</FPHeader>
<lineItem coaCode="ACAE">2578.000000</lineItem>
<lineItem coaCode="ASTI">1860.000000</lineItem>
<lineItem coaCode="SCSI">4438.000000</lineItem>
<lineItem coaCode="AACR">3567.000000</lineItem>
<lineItem coaCode="ATRC">3567.000000</lineItem>
<lineItem coaCode="AITL">2813.000000</lineItem>
<lineItem coaCode="APPY">1964.000000</lineItem>
<lineItem coaCode="SOCA">206.000000</lineItem>
<lineItem coaCode="ATCA">12988.000000</lineItem>
<lineItem coaCode="APTC">12712.000000</lineItem>
<lineItem coaCode="ADEP">-6886.000000</lineItem>
<lineItem coaCode="APPN">5826.000000</lineItem>
<lineItem coaCode="AGWI">9752.000000</lineItem>
<lineItem coaCode="AINT">5311.000000</lineItem>
<lineItem coaCode="SINV">3339.000000</lineItem>
<lineItem coaCode="SOLA">2615.000000</lineItem>
<lineItem coaCode="ATOT">39831.000000</lineItem>
<lineItem coaCode="LAPB">1153.000000</lineItem>
<lineItem coaCode="LAEX">3487.000000</lineItem>
<lineItem coaCode="LSTD">2376.000000</lineItem>
<lineItem coaCode="LCLD">4.000000</lineItem>
<lineItem coaCode="SOCL">1653.000000</lineItem>
<lineItem coaCode="LTCL">8673.000000</lineItem>
<lineItem coaCode="LLTD">6016.000000</lineItem>
<lineItem coaCode="LTTD">6016.000000</lineItem>
<lineItem coaCode="STLD">8396.000000</lineItem>
<lineItem coaCode="LMIN">120.000000</lineItem>
<lineItem coaCode="SLTL">4347.000000</lineItem>
<lineItem coaCode="LTLL">19156.000000</lineItem>
<lineItem coaCode="SCMS">12835.000000</lineItem>
<lineItem coaCode="QRED">25884.000000</lineItem>
<lineItem coaCode="QTSC">-10821.000000</lineItem>
<lineItem coaCode="QUGL">-691.000000</lineItem>
<lineItem coaCode="SOTE">-6532.000000</lineItem>
<lineItem coaCode="QTLE">20675.000000</lineItem>
<lineItem coaCode="QTEL">39831.000000</lineItem>
<lineItem coaCode="QTCO">1469.995420</lineItem>
<lineItem coaCode="STBP">3.817700</lineItem>
</Statement>
<Statement Type="CAS">
<FPHeader>
<PeriodLength>6</PeriodLength>
<periodType Code="M">Months</periodType>
<UpdateType Code="UPD">Updated Normal</UpdateType>
<StatementDate>2016-06-30</StatementDate>
<Source Date="2016-08-03">10-Q</Source>
</FPHeader>
<lineItem coaCode="ONET">931.000000</lineItem>
<lineItem coaCode="SDED">405.000000</lineItem>
<lineItem coaCode="SAMT">289.000000</lineItem>
<lineItem coaCode="SNCI">-510.000000</lineItem>
<lineItem coaCode="SOCF">-299.000000</lineItem>
<lineItem coaCode="OTLO">816.000000</lineItem>
<lineItem coaCode="SCEX">-490.000000</lineItem>
<lineItem coaCode="SICF">-754.000000</lineItem>
<lineItem coaCode="ITLI">-1244.000000</lineItem>
<lineItem coaCode="SFCF">-157.000000</lineItem>
<lineItem coaCode="FCDP">-769.000000</lineItem>
<lineItem coaCode="FPSS">-390.000000</lineItem>
<lineItem coaCode="FPRD">-295.000000</lineItem>
<lineItem coaCode="FTLF">-1611.000000</lineItem>
<lineItem coaCode="SFEE">-384.000000</lineItem>
<lineItem coaCode="SNCC">-2423.000000</lineItem>
</Statement>
</FiscalPeriod>
</InterimPeriods>
</FinancialStatements>
</ReportFinancialStatements>
